endpoints/__init__.py
endpoints/_endpointscfg_impl.py
endpoints/_endpointscfg_setup.py
endpoints/api_config.py
endpoints/api_config_manager.py
endpoints/api_exceptions.py
endpoints/api_request.py
endpoints/apiserving.py
endpoints/constants.py
endpoints/directory_list_generator.py
endpoints/discovery_generator.py
endpoints/discovery_service.py
endpoints/endpoints_dispatcher.py
endpoints/endpointscfg.py
endpoints/errors.py
endpoints/generated_error_info.py
endpoints/message_parser.py
endpoints/openapi_generator.py
endpoints/parameter_converter.py
endpoints/protojson.py
endpoints/proxy.html
endpoints/resource_container.py
endpoints/types.py
endpoints/users_id_token.py
endpoints/util.py
google_endpoints-4.7.0.data/scripts/endpointscfg.py
google_endpoints-4.7.0.dist-info/DESCRIPTION.rst
google_endpoints-4.7.0.dist-info/METADATA
google_endpoints-4.7.0.dist-info/RECORD
google_endpoints-4.7.0.dist-info/WHEEL
google_endpoints-4.7.0.dist-info/metadata.json
google_endpoints-4.7.0.dist-info/top_level.txt
