Metadata-Version: 2.0
Name: google-endpoints
Version: 4.7.0
Summary: Google Cloud Endpoints
Home-page: https://github.com/cloudendpoints/endpoints-python
Author: Google Endpoints Authors
Author-email: googleapis-packages@google.com
License: Apache
Platform: UNKNOWN
Classifier: Development Status :: 4 - Beta
Classifier: Intended Audience :: Developers
Classifier: License :: OSI Approved :: Apache Software License
Classifier: Programming Language :: Python
Classifier: Programming Language :: Python :: 2
Classifier: Programming Language :: Python :: 2.7
Classifier: Programming Language :: Python :: Implementation :: CPython
Requires-Dist: attrs (==17.4.0)
Requires-Dist: google-endpoints-api-management (>=1.10.0)
Requires-Dist: semver (==2.7.7)
Requires-Dist: setuptools (>=36.2.5)
